Sources /decode_stage.v
// DECODE STAGE - ID
module decode_stage (
    input  wire        CLK,
    input  wire        RESET,

    // From IF/ID
    input  wire [31:0] InstrD,
    input  wire [31:0] PCD,
    input  wire [31:0] PCPlus4D,

    // From WB stage
    input  wire        RegWriteW,
    input  wire [4:0]  RDW,
    input  wire [31:0] ResultW,
    // Flush ID/EX 
    input  wire        ClearE,

    // Outputs to EX stage
    output reg         RegWriteE,
    output reg  [1:0]  ResultSrcE,
    output reg         MemWriteE,
    output reg         MemtoRegE,
    output reg         BranchE,
    output reg         JalE,
    output reg         JalrE,
    output reg         ALUSrcE,
    output reg  [4:0]  ALUControlE,
    output reg  [4:0]  ShamtE,
    output reg  [31:0] RD1E,
    output reg  [31:0] RD2E,
    output reg  [31:0] PCE,
    output reg  [31:0] Imm_Ext_E,
    output reg  [31:0] PCPlus4E,
    output reg  [4:0]  RS1E,
    output reg  [4:0]  RS2E,
    output reg  [4:0]  RDE,

    // For hazard unit
    output wire [4:0]  RS1D,
    output wire [4:0]  RS2D
);

    // Instruction
    wire [6:0] op     = InstrD[6:0];
    wire [2:0] funct3 = InstrD[14:12];
    wire [6:0] funct7 = InstrD[31:25];
    wire [4:0] rs1    = InstrD[19:15];
    wire [4:0] rs2    = InstrD[24:20];
    wire [4:0] rd     = InstrD[11:7];
    wire [4:0] shamt  = InstrD[24:20];

    assign RS1D = rs1;
    assign RS2D = rs2;

    // Control Unit
    wire        RegWriteD;
    wire [1:0]  ResultSrcD;
    wire        MemWriteD;
    wire        MemtoRegD;
    wire        BranchD;
    wire        JalD;
    wire        JalrD;
    wire        ALUSrcD;
    wire [1:0]  ImmSrcD;
    wire [1:0]  ALUOpD;
    wire [4:0]  ALUControlD;

    control_unit u_ctrl (
        .op         (op),
        .funct3     (funct3),
        .funct7     (funct7),
        .RegWrite   (RegWriteD),
        .ResultSrc  (ResultSrcD),
        .MemWrite   (MemWriteD),
        .MemtoReg   (MemtoRegD),
        .Branch     (BranchD),
        .Jal        (JalD),
        .Jalr       (JalrD),
        .ALUSrc     (ALUSrcD),
        .ImmSrc     (ImmSrcD),
        .ALUControl (ALUControlD)
    );

    // Register File
    wire [31:0] RD1D, RD2D;

    regfile u_regfile (
        .CLK          (CLK),
        .write_enable (RegWriteW),
        .read_rs1     (rs1),
        .read_rs2     (rs2),
        .write_reg    (RDW),
        .write_data   (ResultW),
        .read_data_rs1(RD1D),
        .read_data_rs2(RD2D)
    );

    // Sign Extend 
    wire [31:0] ImmExtD;

    extend u_extend (
        .Instr   (InstrD[31:7]),
        .ImmSrc  (ImmSrcD),
        .ImmExt  (ImmExtD)
    );

    // ID/EX Pipeline Register 
    always @(posedge CLK or posedge RESET) begin
        if (RESET || ClearE) begin
            RegWriteE   <= 1'b0;
            ResultSrcE  <= 2'b00;
            MemWriteE   <= 1'b0;
            MemtoRegE   <= 1'b0;
            BranchE     <= 1'b0;
            JalE        <= 1'b0;
            JalrE       <= 1'b0;
            ALUSrcE     <= 1'b0;
            ALUControlE <= 5'b00000;
            ShamtE      <= 5'b00000;
            RD1E        <= 32'd0;
            RD2E        <= 32'd0;
            PCE         <= 32'd0;
            Imm_Ext_E   <= 32'd0;
            PCPlus4E    <= 32'd0;
            RS1E        <= 5'd0;
            RS2E        <= 5'd0;
            RDE         <= 5'd0;
        end else begin
            RegWriteE   <= RegWriteD;
            ResultSrcE  <= ResultSrcD;
            MemWriteE   <= MemWriteD;
            MemtoRegE   <= MemtoRegD;
            BranchE     <= BranchD;
            JalE        <= JalD;
            JalrE       <= JalrD;
            ALUSrcE     <= ALUSrcD;
            ALUControlE <= ALUControlD;
            ShamtE      <= shamt;
            RD1E        <= RD1D;
            RD2E        <= RD2D;
            PCE         <= PCD;
            Imm_Ext_E   <= ImmExtD;
            PCPlus4E    <= PCPlus4D;
            RS1E        <= rs1;
            RS2E        <= rs2;
            RDE         <= rd;
        end
    end

endmodule


// Control Unit
module control_unit (
    input  wire [6:0] op,
    input  wire [2:0] funct3,
    input  wire [6:0] funct7,
    output reg        RegWrite,
    output reg  [1:0] ResultSrc,
    output reg        MemWrite,
    output reg        MemtoReg,
    output reg        Branch,
    output reg        Jal,
    output reg        Jalr,
    output reg        ALUSrc,
    output reg  [1:0] ImmSrc,
    output reg  [4:0] ALUControl
);
    reg [1:0] ALUOp;

    always @(*) begin
        // defaults
        RegWrite  = 1'b0;
        ResultSrc = 2'b00;
        MemWrite  = 1'b0;
        MemtoReg  = 1'b0;
        Branch    = 1'b0;
        Jal       = 1'b0;
        Jalr      = 1'b0;
        ALUSrc    = 1'b0;
        ImmSrc    = 2'b00;
        ALUOp     = 2'b00;

        case (op)
            7'b0000011: begin // I-Type Load 
                RegWrite  = 1'b1;
                ResultSrc = 2'b01; // From memory
                MemtoReg  = 1'b1;
                ALUSrc    = 1'b1;
                ImmSrc    = 2'b00;
                ALUOp     = 2'b00;
            end
            7'b0100011: begin // S-Type Store
                MemWrite  = 1'b1;
                ALUSrc    = 1'b1;
                ImmSrc    = 2'b01;
                ALUOp     = 2'b00;
            end
            7'b1100011: begin // B-Type Branch
                Branch    = 1'b1;
                ImmSrc    = 2'b10;
                ALUOp     = 2'b01;
            end
            7'b1100111: begin // J-Type JALR
                RegWrite  = 1'b1;
                ResultSrc = 2'b10; 
                Jal       = 1'b1;
                Jalr      = 1'b1;
                ALUSrc    = 1'b1;
                ImmSrc    = 2'b00;
                ALUOp     = 2'b01;
            end
            7'b0010011: begin // I-Type Arithmetic 
                RegWrite  = 1'b1;
                ResultSrc = 2'b00;
                ALUSrc    = 1'b1;
                ImmSrc    = 2'b00;
                ALUOp     = 2'b10;
            end
            7'b0110011: begin // R-Type Arithmetic
                RegWrite  = 1'b1;
                ResultSrc = 2'b00;
                ALUOp     = 2'b10;
            end
            7'b1101111: begin // J-Type JAL
                RegWrite  = 1'b1;
                ResultSrc = 2'b10; 
                Jal       = 1'b1;
                ImmSrc    = 2'b11;
                ALUOp     = 2'b11;
            end
            default: begin end
        endcase
    end

  
    wire [2:0] aluop_combo = {op[5], funct7[5], op[2]};

    always @(*) begin
        ALUControl = 5'b00000;
        case (ALUOp)
            2'b00: ALUControl = 5'b00000; // LW/SW -> ADD
            2'b01: begin // Branch/JALR
                case (funct3)
                    3'b000: ALUControl = (aluop_combo[1] == 1'b1 && aluop_combo[0] == 1'b0) ?
                                          5'b00001 : // BEQ
                                          5'b00010;  // JALR 
                    3'b001: ALUControl = 5'b00011;   // BNE
                    3'b100: ALUControl = 5'b00100;   // BLT
                    3'b101: ALUControl = 5'b00101;   // BGE
                    default: ALUControl = 5'b00001;
                endcase
            end
            2'b10: begin // Logic and Arithmetic
                case (funct3)
                    3'b000: begin
                        if (aluop_combo == 3'b110)
                            ALUControl = 5'b00111; // SUB
                        else
                            ALUControl = 5'b00110; // ADD/ADDI
                    end
                    3'b001: begin
                        if (aluop_combo[2] == 1'b1)
                            ALUControl = 5'b01000; // SLL
                        else
                            ALUControl = 5'b01001; // SLLI
                    end
                    3'b010: ALUControl = 5'b01010;  // SLT/SLTI
                    3'b100: ALUControl = 5'b01011;  // XOR/XORI
                    3'b101: begin
                        case (aluop_combo)
                            3'b100: ALUControl = 5'b01100; // SRL
                            3'b110: ALUControl = 5'b01101; // SRA
                            3'b000: ALUControl = 5'b01110; // SRLI
                            3'b010: ALUControl = 5'b01111; // SRAI
                            default: ALUControl = 5'b01100;
                        endcase
                    end
                    3'b110: ALUControl = 5'b10000;  // OR/ORI
                    3'b111: ALUControl = 5'b10001;  // AND/ANDI
                    default: ALUControl = 5'b00110;
                endcase
            end
            2'b11: ALUControl = 5'b10010; // JAL
            default: ALUControl = 5'b00000;
        endcase
    end

endmodule


// Register File - 32 x 32-bit registers
module regfile (
    input  wire        CLK,
    input  wire        write_enable,
    input  wire [4:0]  read_rs1,
    input  wire [4:0]  read_rs2,
    input  wire [4:0]  write_reg,
    input  wire [31:0] write_data,
    output wire [31:0] read_data_rs1,
    output wire [31:0] read_data_rs2
);
    reg [31:0] regs [0:31];
    integer i;
    initial begin
        // for (i = 0; i < 32; i = i + 1)
          //  regs[i] = 32'd0;
	regs[0] = 32'd0;
	regs[1] = 32'd1;
	regs[2] = 32'd2;
	regs[3] = 32'd3;
	regs[4] = 32'd4;
	regs[5] = 32'd5;
	regs[6] = 32'd6;
	regs[7] = 32'd7;
	regs[8] = 32'd8;
	regs[9] = 32'd9;
	regs[10] = 32'd10;
	regs[11] = 32'd11;
	regs[12] = 32'd12;
	regs[13] = 32'd13;
	regs[14] = 32'd14;
	regs[15] = 32'd15;
	regs[16] = 32'd16;
	regs[17] = 32'd17;
	regs[18] = 32'd18;
	regs[19] = 32'd19;
	regs[20] = 32'd20;
	regs[21] = 32'd21;
	regs[22] = 32'd22;
	regs[23] = 32'd23;
	regs[24] = 32'd24;
	regs[25] = 32'd25;
	regs[26] = 32'd26;
	regs[27] = 32'd27;
	regs[28] = 32'd28;
	regs[29] = 32'd29;
	regs[30] = 32'd30;
	regs[31] = 32'd31;
    end

    always @(posedge CLK) begin
        if (write_enable && write_reg != 5'd0)
            regs[write_reg] <= write_data;
    end

    assign read_data_rs1 = (read_rs1 == 5'd0) ? 32'd0 :
                           (write_enable && write_reg == read_rs1) ? write_data :
                           regs[read_rs1];
    assign read_data_rs2 = (read_rs2 == 5'd0) ? 32'd0 :
                           (write_enable && write_reg == read_rs2) ? write_data :
                           regs[read_rs2];
endmodule


// Sign/Zero Extend 
module extend (
    input  wire [31:7] Instr,   
    input  wire [1:0]  ImmSrc,
    output reg  [31:0] ImmExt
);
    always @(*) begin
        case (ImmSrc)
            2'b00: // I-type
                ImmExt = {{20{Instr[31]}}, Instr[31:20]};
            2'b01: // S-type
                ImmExt = {{20{Instr[31]}}, Instr[31:25], Instr[11:7]};
            2'b10: // B-type
                ImmExt = {{19{Instr[31]}}, Instr[31], Instr[7], Instr[30:25], Instr[11:8], 1'b0};
            2'b11: // J-type (JAL)
                ImmExt = {{11{Instr[31]}}, Instr[31], Instr[19:12], Instr[20], Instr[30:21], 1'b0};
            default: ImmExt = 32'd0;
        endcase
    end
endmodule

tb/tb_decode_stage.v
`timescale 1ns / 1ps

module tb_decode_stage;

    // ---------------------------------------------------------
    // 1. Signal Declarations
    // ---------------------------------------------------------
    reg         CLK;
    reg         RESET;

    // Inputs from IF/ID stage
    reg  [31:0] InstrD;
    reg  [31:0] PCD;
    reg  [31:0] PCPlus4D;

    // Feedback inputs from WB (Writeback) stage
    reg         RegWriteW;
    reg  [4:0]  RDW;
    reg  [31:0] ResultW;
    
    // Pipeline flush signal
    reg         ClearE;

    // Outputs forwarded to EX (Execute) stage
    wire        RegWriteE;
    wire [1:0]  ResultSrcE;
    wire        MemWriteE;
    wire        MemtoRegE;
    wire        BranchE;
    wire        JalE;
    wire        JalrE;
    wire        ALUSrcE;
    wire [4:0]  ALUControlE;
    wire [4:0]  ShamtE;
    wire [31:0] RD1E;
    wire [31:0] RD2E;
    wire [31:0] PCE;
    wire [31:0] Imm_Ext_E;
    wire [31:0] PCPlus4E;
    wire [4:0]  RS1E;
    wire [4:0]  RS2E;
    wire [4:0]  RDE;

    // Outputs to Hazard Unit
    wire [4:0]  RS1D;
    wire [4:0]  RS2D;

    // ---------------------------------------------------------
    // 2. Unit Under Test (UUT) Instantiation
    // ---------------------------------------------------------
    decode_stage uut (
        .CLK(CLK),
        .RESET(RESET),
        .InstrD(InstrD),
        .PCD(PCD),
        .PCPlus4D(PCPlus4D),
        .RegWriteW(RegWriteW),
        .RDW(RDW),
        .ResultW(ResultW),
        .ClearE(ClearE),
        .RegWriteE(RegWriteE),
        .ResultSrcE(ResultSrcE),
        .MemWriteE(MemWriteE),
        .MemtoRegE(MemtoRegE),
        .BranchE(BranchE),
        .JalE(JalE),
        .JalrE(JalrE),
        .ALUSrcE(ALUSrcE),
        .ALUControlE(ALUControlE),
        .ShamtE(ShamtE),
        .RD1E(RD1E),
        .RD2E(RD2E),
        .PCE(PCE),
        .Imm_Ext_E(Imm_Ext_E),
        .PCPlus4E(PCPlus4E),
        .RS1E(RS1E),
        .RS2E(RS2E),
        .RDE(RDE),
        .RS1D(RS1D),
        .RS2D(RS2D)
    );

    // ---------------------------------------------------------
    // 3. Clock Generation (10ns Period -> 100MHz)
    // ---------------------------------------------------------
    always #5 CLK = ~CLK;

    // ---------------------------------------------------------
    // 4. Test Stimulus Process
    // ---------------------------------------------------------
    initial begin
        // --- Step 1: System Initialization ---
        CLK = 0;
        RESET = 1;
        InstrD = 32'd0;
        PCD = 32'd0;
        PCPlus4D = 32'd0;
        RegWriteW = 0;
        RDW = 5'd0;
        ResultW = 32'd0;
        ClearE = 0;

        // Hold reset for 2 clock cycles for system stability
        #20;
        RESET = 0;
        #10;

        $display("==================================================");
        $display("   STARTING TESTBENCH: DECODE STAGE               ");
        $display("==================================================");

        // -------------------------------------------------------------
        // Scenario 1: Test R-type instruction (ADD x3, x1, x2)
        // Background: Your regfile initializes regs[1]=1, regs[2]=2.
        // Expected RISC-V machine code: 32'h002081B3
        // -------------------------------------------------------------
        $display("\n[Scenario 1] Testing R-type decoding: ADD x3, x1, x2");
        PCD      = 32'h00001000;
        PCPlus4D = 32'h00001004;
        InstrD   = 32'h002081B3; 
        #10; // Wait for the next rising edge of CLK to push data into ID/EX Reg
        
        if (RegWriteE === 1'b1 && ALUControlE === 5'b00110 && RD1E === 32'd1 && RD2E === 32'd2)
            $display(" -> SUCCESS: R-type instruction decoded correctly with accurate control signals.");
        else
            $display(" -> FAILURE: R-type error! RD1E=%d, RD2E=%d, ALUControlE=%b", RD1E, RD2E, ALUControlE);


        // -------------------------------------------------------------
        // Scenario 2: Test I-type immediate instruction (ADDI x4, x1, 10)
        // Expected machine code: 32'h00A08213 (Immediate = 10)
        // -------------------------------------------------------------
        $display("\n[Scenario 2] Testing I-type decoding: ADDI x4, x1, 10");
        InstrD   = 32'h00A08213;
        #10;
        
        if (ALUSrcE === 1'b1 && Imm_Ext_E === 32'd10 && RDE === 5'd4)
            $display(" -> SUCCESS: I-type instruction generated correct sign-extended immediate.");
        else
            $display(" -> FAILURE: I-type error! ALUSrcE=%b, Imm_Ext_E=%d", ALUSrcE, Imm_Ext_E);


        // -------------------------------------------------------------
        // Scenario 3: Test Internal Forwarding in RegFile (Simultaneous Read/Write)
        // Context: WB stage writes a new value (0xABCDEFFF) to x1.
        // Simultaneously, Decode stage attempts to read x1.
        // Your regfile design must bypass and output this new value immediately.
        // -------------------------------------------------------------
        $display("\n[Scenario 3] Testing Internal Forwarding (Simultaneous R/W on x1)");
        RegWriteW = 1'b1;
        RDW       = 5'd1;
        ResultW   = 32'hABCDEFFF;
        // Keep the same ADDI instruction so Decode continues to sample x1
        #10; 
        
        if (RD1E === 32'hABCDEFFF)
            $display(" -> SUCCESS: Internal forwarding (bypass) within RegFile works correctly.");
        else
            $display(" -> FAILURE: Forwarding data mismatch! RD1E=%h (Expected: ABCDEFFF)", RD1E);

        // Reset WB control signals
        RegWriteW = 1'b0;


        // -------------------------------------------------------------
        // Scenario 4: Test Load Word instruction (LW x5, 4(x2))
        // Expected machine code: 32'h00412283
        // -------------------------------------------------------------
        $display("\n[Scenario 4] Testing Load Word decoding: LW x5, 4(x2)");
        InstrD   = 32'h00412283;
        #10;
        
        if (MemtoRegE === 1'b1 && ResultSrcE === 2'b01 && RegWriteE === 1'b1)
            $display(" -> SUCCESS: Memory load control signals (MemtoReg, ResultSrc) are correctly asserted.");
        else
            $display(" -> FAILURE: Incorrect control signals for Load instruction.");


        // -------------------------------------------------------------
        // Scenario 5: Test ClearE pin (Pipeline Flush / Bubble insertion)
        // When ClearE is active, on the next rising clock edge, all ID/EX 
        // buffer values must clear back to 0.
        // -------------------------------------------------------------
        $display("\n[Scenario 5] Testing Pipeline Flush (ClearE / Flush)");
        ClearE = 1'b1;
        #10;
        
        if (RegWriteE === 1'b0 && MemWriteE === 1'b0 && RD1E === 32'd0 && RDE === 5'd0)
            $display(" -> SUCCESS: ID/EX pipeline register successfully flushed to 0.");
        else
            $display(" -> FAILURE: ClearE signal failed to flush EX stage data.");
        
        ClearE = 1'b0; // Disable flush after check


        // -------------------------------------------------------------
        // Scenario 6: Test B-type Branch instruction (BEQ x1, x2, offset 16)
        // Expected machine code: 32'h00208863
        // -------------------------------------------------------------
        $display("\n[Scenario 6] Testing Branch decoding: BEQ x1, x2, offset 16");
        InstrD   = 32'h00208863;
        #10;
        
        if (BranchE === 1'b1 && Imm_Ext_E === 32'd16)
            $display(" -> SUCCESS: B-type immediate extension generated accurately.");
        else
            $display(" -> FAILURE: Branch structural error! BranchE=%b, Imm_Ext_E=%d", BranchE, Imm_Ext_E);


        // --- End Simulation ---
        $display("\n==================================================");
        $display("   TESTBENCH COMPLETED: DECODE STAGE              ");
        $display("==================================================");
        $finish;
    end

    // (Optional) Dump Waveform for GTKWave/Vivado
    initial begin
        $dumpfile("decode_stage_tb.vcd");
        $dumpvars(0, tb_decode_stage);
    end

endmodule

decode_stage_tb.vcd
$date
	Tue Jun 23 08:35:24 2026
$end
$version
	Icarus Verilog
$end
$timescale
	1ps
$end
$scope module tb_decode_stage $end
$var wire 5 ! ShamtE [4:0] $end
$var wire 2 " ResultSrcE [1:0] $end
$var wire 1 # RegWriteE $end
$var wire 5 $ RS2E [4:0] $end
$var wire 5 % RS2D [4:0] $end
$var wire 5 & RS1E [4:0] $end
$var wire 5 ' RS1D [4:0] $end
$var wire 5 ( RDE [4:0] $end
$var wire 32 ) RD2E [31:0] $end
$var wire 32 * RD1E [31:0] $end
$var wire 32 + PCPlus4E [31:0] $end
$var wire 32 , PCE [31:0] $end
$var wire 1 - MemtoRegE $end
$var wire 1 . MemWriteE $end
$var wire 1 / JalrE $end
$var wire 1 0 JalE $end
$var wire 32 1 Imm_Ext_E [31:0] $end
$var wire 1 2 BranchE $end
$var wire 1 3 ALUSrcE $end
$var wire 5 4 ALUControlE [4:0] $end
$var reg 1 5 CLK $end
$var reg 1 6 ClearE $end
$var reg 32 7 InstrD [31:0] $end
$var reg 32 8 PCD [31:0] $end
$var reg 32 9 PCPlus4D [31:0] $end
$var reg 5 : RDW [4:0] $end
$var reg 1 ; RESET $end
$var reg 1 < RegWriteW $end
$var reg 32 = ResultW [31:0] $end
$scope module uut $end
$var wire 1 5 CLK $end
$var wire 1 6 ClearE $end
$var wire 32 > InstrD [31:0] $end
$var wire 32 ? PCD [31:0] $end
$var wire 32 @ PCPlus4D [31:0] $end
$var wire 5 A RDW [4:0] $end
$var wire 1 ; RESET $end
$var wire 5 B RS1D [4:0] $end
$var wire 5 C RS2D [4:0] $end
$var wire 1 < RegWriteW $end
$var wire 32 D ResultW [31:0] $end
$var wire 5 E shamt [4:0] $end
$var wire 5 F rs2 [4:0] $end
$var wire 5 G rs1 [4:0] $end
$var wire 5 H rd [4:0] $end
$var wire 7 I op [6:0] $end
$var wire 7 J funct7 [6:0] $end
$var wire 3 K funct3 [2:0] $end
$var wire 2 L ResultSrcD [1:0] $end
$var wire 1 M RegWriteD $end
$var wire 32 N RD2D [31:0] $end
$var wire 32 O RD1D [31:0] $end
$var wire 1 P MemtoRegD $end
$var wire 1 Q MemWriteD $end
$var wire 1 R JalrD $end
$var wire 1 S JalD $end
$var wire 2 T ImmSrcD [1:0] $end
$var wire 32 U ImmExtD [31:0] $end
$var wire 1 V BranchD $end
$var wire 1 W ALUSrcD $end
$var wire 5 X ALUControlD [4:0] $end
$var reg 5 Y ALUControlE [4:0] $end
$var reg 1 3 ALUSrcE $end
$var reg 1 2 BranchE $end
$var reg 32 Z Imm_Ext_E [31:0] $end
$var reg 1 0 JalE $end
$var reg 1 / JalrE $end
$var reg 1 . MemWriteE $end
$var reg 1 - MemtoRegE $end
$var reg 32 [ PCE [31:0] $end
$var reg 32 \ PCPlus4E [31:0] $end
$var reg 32 ] RD1E [31:0] $end
$var reg 32 ^ RD2E [31:0] $end
$var reg 5 _ RDE [4:0] $end
$var reg 5 ` RS1E [4:0] $end
$var reg 5 a RS2E [4:0] $end
$var reg 1 # RegWriteE $end
$var reg 2 b ResultSrcE [1:0] $end
$var reg 5 c ShamtE [4:0] $end
$scope module u_ctrl $end
$var wire 3 d funct3 [2:0] $end
$var wire 7 e funct7 [6:0] $end
$var wire 7 f op [6:0] $end
$var wire 3 g aluop_combo [2:0] $end
$var reg 5 h ALUControl [4:0] $end
$var reg 2 i ALUOp [1:0] $end
$var reg 1 W ALUSrc $end
$var reg 1 V Branch $end
$var reg 2 j ImmSrc [1:0] $end
$var reg 1 S Jal $end
$var reg 1 R Jalr $end
$var reg 1 Q MemWrite $end
$var reg 1 P MemtoReg $end
$var reg 1 M RegWrite $end
$var reg 2 k ResultSrc [1:0] $end
$upscope $end
$scope module u_extend $end
$var wire 2 l ImmSrc [1:0] $end
$var wire 25 m Instr [31:7] $end
$var reg 32 n ImmExt [31:0] $end
$upscope $end
$scope module u_regfile $end
$var wire 1 5 CLK $end
$var wire 5 o read_rs1 [4:0] $end
$var wire 5 p read_rs2 [4:0] $end
$var wire 32 q write_data [31:0] $end
$var wire 1 < write_enable $end
$var wire 5 r write_reg [4:0] $end
$var wire 32 s read_data_rs2 [31:0] $end
$var wire 32 t read_data_rs1 [31:0] $end
$upscope $end
$upscope $end
$upscope $end
$enddefinitions $end
$comment Show the parameter values. $end
$dumpall
$end
#0
$dumpvars
b0 t
b0 s
b0 r
b0 q
b0 p
b0 o
b0 n
b0 m
b0 l
b0 k
b0 j
b0 i
b0 h
b0 g
b0 f
b0 e
b0 d
b0 c
b0 b
b0 a
b0 `
b0 _
b0 ^
b0 ]
b0 \
b0 [
b0 Z
b0 Y
b0 X
0W
0V
b0 U
b0 T
0S
0R
0Q
0P
b0 O
b0 N
0M
b0 L
b0 K
b0 J
b0 I
b0 H
b0 G
b0 F
b0 E
b0 D
b0 C
b0 B
b0 A
b0 @
b0 ?
b0 >
b0 =
0<
1;
b0 :
b0 9
b0 8
b0 7
06
05
b0 4
03
02
b0 1
00
0/
0.
0-
b0 ,
b0 +
b0 *
b0 )
b0 (
b0 '
b0 &
b0 %
b0 $
0#
b0 "
b0 !
$end
#5000
15
#10000
05
#15000
15
#20000
05
0;
#25000
15
#30000
b110 X
b110 h
b10 i
1M
b100 g
b1 O
b1 t
b10 N
b10 s
b10 U
b10 n
b110011 I
b110011 f
b1 '
b1 B
b1 G
b1 o
b10 %
b10 C
b10 F
b10 p
b11 H
b10 E
b100000100000011 m
05
b1000001000000110110011 7
b1000001000000110110011 >
b1000000000100 9
b1000000000100 @
b1000000000000 8
b1000000000000 ?
#35000
b11 (
b11 _
b10 $
b10 a
b1 &
b1 `
b1000000000100 +
b1000000000100 \
b10 1
b10 Z
b1000000000000 ,
b1000000000000 [
b10 )
b10 ^
b1 *
b1 ]
b10 !
b10 c
b110 4
b110 Y
1#
15
#40000
b110 X
b110 h
b1010 N
b1010 s
1W
b10 i
1M
b0 g
b1010 U
b1010 n
b10011 I
b10011 f
b1010 %
b1010 C
b1010 F
b1010 p
b100 H
b1010 E
b10100000100000100 m
05
b101000001000001000010011 7
b101000001000001000010011 >
#45000
b100 (
b100 _
b1010 $
b1010 a
b1010 1
b1010 Z
b1010 )
b1010 ^
b1010 !
b1010 c
13
15
#50000
b10101011110011011110111111111111 O
b10101011110011011110111111111111 t
05
b10101011110011011110111111111111 =
b10101011110011011110111111111111 D
b10101011110011011110111111111111 q
b1 :
b1 A
b1 r
1<
#55000
b10101011110011011110111111111111 *
b10101011110011011110111111111111 ]
15
#60000
b100 N
b100 s
b10 O
b10 t
1P
b1 L
b1 k
b0 i
1W
1M
b0 X
b0 h
b100 U
b100 n
b11 I
b11 f
b10 K
b10 d
b10 '
b10 B
b10 G
b10 o
b100 %
b100 C
b100 F
b100 p
b101 H
b100 E
b1000001001000101 m
05
b10000010010001010000011 7
b10000010010001010000011 >
0<
#65000
b101 (
b101 _
b100 $
b100 a
b10 &
b10 `
b100 1
b100 Z
b100 )
b100 ^
b10 *
b10 ]
b100 !
b100 c
b0 4
b0 Y
1-
b1 "
b1 b
15
#70000
05
16
#75000
b0 (
b0 _
b0 $
b0 a
b0 &
b0 `
b0 +
b0 \
b0 1
b0 Z
b0 ,
b0 [
b0 )
b0 ^
b0 *
b0 ]
b0 !
b0 c
03
0-
b0 "
b0 b
0#
15
#80000
b10 X
b10 h
b10101011110011011110111111111111 O
b10101011110011011110111111111111 t
b10 N
b10 s
b1 i
b10 T
b10 j
b10 l
1V
0W
0P
b0 L
b0 k
0M
b100 g
b10000 U
b10000 n
b1100011 I
b1100011 f
b0 K
b0 d
b1 '
b1 B
b1 G
b1 o
b10 %
b10 C
b10 F
b10 p
b10000 H
b10 E
b100000100010000 m
05
b1000001000100001100011 7
b1000001000100001100011 >
06
#85000
b10000 (
b10000 _
b10 $
b10 a
b1 &
b1 `
b1000000000100 +
b1000000000100 \
b10000 1
b10000 Z
b1000000000000 ,
b1000000000000 [
b10 )
b10 ^
b10101011110011011110111111111111 *
b10101011110011011110111111111111 ]
b10 !
b10 c
b10 4
b10 Y
12
15
