rtl/execute_stage.v
// EXECUTE STAGE - EX

module execute_stage (
    input  wire        CLK,
    input  wire        RESET,

    // From ID/EX
    input  wire        RegWriteE,
    input  wire [1:0]  ResultSrcE,
    input  wire        MemWriteE,
    input  wire        BranchE,
    input  wire        JalE,
    input  wire        JalrE,
    input  wire        ALUSrcE,
    input  wire [4:0]  ALUControlE,
    input  wire [4:0]  ShamtE,

    // From ID/EX
    input  wire [31:0] RD1E,
    input  wire [31:0] RD2E,
    input  wire [31:0] PCE,
    input  wire [31:0] Imm_Ext_E,
    input  wire [31:0] PCPlus4E,
    input  wire [4:0]  RDE,
    input  wire [4:0]  RS1E,
    input  wire [4:0]  RS2E,

    // From Hazard Unit
    input  wire [1:0]  ForwardAE,
    input  wire [1:0]  ForwardBE,

    // from EX/MA register
    input  wire [31:0] ALUResultM_fwd,  


    input  wire [31:0] ResultW_fwd,     
    // Outputs
    output wire [1:0]  PCSrcE,
    output wire [31:0] PCTargetE,
    output wire [31:0] ResultE,
    // To EX/MA pipeline register outputs
    output reg  [31:0] ALUResultM,
    output reg  [31:0] WriteDataM,
    output reg         RegWriteM,
    output reg         MemWriteM,
    output reg  [1:0]  ResultSrcM,
    output reg  [4:0]  RDM,
    output reg  [31:0] PCPlus4M
);

    // Forwarding MUX for SrcA 
    reg [31:0] SrcA_raw;
    always @(*) begin
        case (ForwardAE)
            2'b00: SrcA_raw = RD1E;
            2'b01: SrcA_raw = ResultW_fwd;
            2'b10: SrcA_raw = ALUResultM_fwd;
            default: SrcA_raw = RD1E;
        endcase
    end

    // Forwarding MUX for SrcB 
    reg [31:0] SrcB_reg_fwd;
    always @(*) begin
        case (ForwardBE)
            2'b00: SrcB_reg_fwd = RD2E;
            2'b01: SrcB_reg_fwd = ResultW_fwd;
            2'b10: SrcB_reg_fwd = ALUResultM_fwd;
            default: SrcB_reg_fwd = RD2E;
        endcase
    end

    //  ALUSrc MUX
    wire [31:0] SrcB = ALUSrcE ? Imm_Ext_E : SrcB_reg_fwd;

    //  ALU 
    wire [31:0] ALUResult;
    wire        Zero;

    alu u_alu (
        .SrcA      (SrcA_raw),
        .SrcB      (SrcB),
        .ALUControl(ALUControlE),
        .Shamt     (ShamtE),
        .ALUResult (ALUResult),
        .Zero      (Zero)
    );

   // Branch adder
    assign PCTargetE = PCE + Imm_Ext_E;

   // For JALR to IF
    assign ResultE = ALUResult;

   // PCSrc MUX
    pcsrc_logic u_pcsrc (
        .Zero    (Zero),
        .BranchE (BranchE),
        .JalE    (JalE),
        .JalrE   (JalrE),
        .ALUControlE(ALUControlE),
        .PCSrcE  (PCSrcE)
    );

   //  EX/MA Pipeline Register 
    always @(posedge CLK or posedge RESET) begin
        if (RESET) begin
            ALUResultM <= 32'd0;
            WriteDataM <= 32'd0;
            RegWriteM  <= 1'b0;
            MemWriteM  <= 1'b0;
            ResultSrcM <= 2'b00;
            RDM        <= 5'd0;
            PCPlus4M   <= 32'd0;
        end else begin
            ALUResultM <= ALUResult;
            WriteDataM <= SrcB_reg_fwd; 
            RegWriteM  <= RegWriteE;
            MemWriteM  <= MemWriteE;
            ResultSrcM <= ResultSrcE;
            RDM        <= RDE;
            PCPlus4M   <= PCPlus4E;
        end
    end

endmodule


// ALU - Arithmetic Logic Unit 
module alu (
    input  wire [31:0] SrcA,
    input  wire [31:0] SrcB,
    input  wire [4:0]  ALUControl,
    input  wire [4:0]  Shamt,
    output reg  [31:0] ALUResult,
    output wire        Zero
);
    assign Zero = (ALUResult == 32'd0);

    always @(*) begin
        case (ALUControl)
            5'b00000: ALUResult = SrcA + SrcB;                          // LW/SW ADD
            5'b00001: ALUResult = SrcA - SrcB;                          // BEQ (sub, check zero)
            5'b00010: ALUResult = SrcA + SrcB;                          // JALR (addr calc)
            5'b00011: ALUResult = SrcA - SrcB;                          // BNE
            5'b00100: ALUResult = ($signed(SrcA) < $signed(SrcB)) ? 32'd1 : 32'd0; // BLT
            5'b00101: ALUResult = ($signed(SrcA) >= $signed(SrcB)) ? 32'd1 : 32'd0;// BGE
            5'b00110: ALUResult = SrcA + SrcB;                          // ADD/ADDI
            5'b00111: ALUResult = SrcA - SrcB;                          // SUB
            5'b01000: ALUResult = SrcA << SrcB[4:0];                    // SLL
            5'b01001: ALUResult = SrcA << Shamt;                        // SLLI
            5'b01010: ALUResult = ($signed(SrcA) < $signed(SrcB)) ? 32'd1 : 32'd0; // SLT/SLTI
            5'b01011: ALUResult = SrcA ^ SrcB;                          // XOR/XORI
            5'b01100: ALUResult = SrcA >> SrcB[4:0];                    // SRL
            5'b01101: ALUResult = $signed(SrcA) >>> SrcB[4:0];         // SRA
            5'b01110: ALUResult = SrcA >> Shamt;                        // SRLI
            5'b01111: ALUResult = $signed(SrcA) >>> Shamt;             // SRAI
            5'b10000: ALUResult = SrcA | SrcB;                          // OR/ORI
            5'b10001: ALUResult = SrcA & SrcB;                          // AND/ANDI
            5'b10010: ALUResult = SrcA + SrcB;                          // JAL (PC+imm handled in adder)
            default:  ALUResult = 32'd0;
        endcase
    end
endmodule


// PCSrc MUX
module pcsrc_logic (
    input  wire        Zero,
    input  wire        BranchE,
    input  wire        JalE,
    input  wire        JalrE,
    input  wire [4:0]  ALUControlE,
    output reg  [1:0]  PCSrcE
);
    
    reg branch_taken;

    always @(*) begin
        branch_taken = 1'b0;
        case (ALUControlE)
            5'b00001: branch_taken = Zero;          // BEQ
            5'b00011: branch_taken = ~Zero;         // BNE
            5'b00100: branch_taken = ~Zero;         // BLT 
            default:  branch_taken = 1'b0;	    // BGE
        endcase
    end

    always @(*) begin
        if (JalrE)
            PCSrcE = 2'b10;
        else if ((BranchE && branch_taken) || JalE)
            PCSrcE = 2'b01;
        else
            PCSrcE = 2'b00;
    end
endmodule

tb/tb_execute_stage.v
`timescale 1ns / 1ps

module tb_execute_stage;

    // ---------------------------------------------------------
    // 1. Signal Declarations
    // ---------------------------------------------------------
    reg         CLK;
    reg         RESET;

    // Control Inputs from ID/EX Register
    reg         RegWriteE;
    reg  [1:0]  ResultSrcE;
    reg         MemWriteE;
    reg         BranchE;
    reg         JalE;
    reg         JalrE;
    reg         ALUSrcE;
    reg  [4:0]  ALUControlE;
    reg  [4:0]  ShamtE;

    // Data Inputs from ID/EX Register
    reg  [31:0] RD1E;
    reg  [31:0] RD2E;
    reg  [31:0] PCE;
    reg  [31:0] Imm_Ext_E;
    reg  [31:0] PCPlus4E;
    reg  [4:0]  RDE;
    reg  [4:0]  RS1E;
    reg  [4:0]  RS2E;

    // Inputs from Hazard Unit (Forwarding Selectors)
    reg  [1:0]  ForwardAE;
    reg  [1:0]  ForwardBE;

    // Forwarded Data Paths
    reg  [31:0] ALUResultM_fwd;  // From Memory Stage (EX/MA)
    reg  [31:0] ResultW_fwd;     // From Writeback Stage (MA/WB)

    // Outputs to Fetch (IF) Stage
    wire [1:0]  PCSrcE;
    wire [31:0] PCTargetE;
    wire [31:0] ResultE;

    // Outputs to EX/MA Pipeline Register
    wire [31:0] ALUResultM;
    wire [31:0] WriteDataM;
    wire        RegWriteM;
    wire        MemWriteM;
    wire [1:0]  ResultSrcM;
    wire [4:0]  RDM;
    wire [31:0] PCPlus4M;

    // ---------------------------------------------------------
    // 2. Unit Under Test (UUT) Instantiation
    // ---------------------------------------------------------
    execute_stage uut (
        .CLK(CLK),
        .RESET(RESET),
        .RegWriteE(RegWriteE),
        .ResultSrcE(ResultSrcE),
        .MemWriteE(MemWriteE),
        .BranchE(BranchE),
        .JalE(JalE),
        .JalrE(JalrE),
        .ALUSrcE(ALUSrcE),
        .ALUControlE(ALUControlE),
        .ShamtE(ShamtE),
        .RD1E(RD1E),
        .RD2E(RD2E),
        .PCE(PCE),
        .Imm_Ext_E(Imm_Ext_E),
        .PCPlus4E(PCPlus4E),
        .RDE(RDE),
        .RS1E(RS1E),
        .RS2E(RS2E),
        .ForwardAE(ForwardAE),
        .ForwardBE(ForwardBE),
        .ALUResultM_fwd(ALUResultM_fwd),
        .ResultW_fwd(ResultW_fwd),
        .PCSrcE(PCSrcE),
        .PCTargetE(PCTargetE),
        .ResultE(ResultE),
        .ALUResultM(ALUResultM),
        .WriteDataM(WriteDataM),
        .RegWriteM(RegWriteM),
        .MemWriteM(MemWriteM),
        .ResultSrcM(ResultSrcM),
        .RDM(RDM),
        .PCPlus4M(PCPlus4M)
    );

    // ---------------------------------------------------------
    // 3. Clock Generation (10ns Period -> 100MHz)
    // ---------------------------------------------------------
    always #5 CLK = ~CLK;

    // ---------------------------------------------------------
    // 4. Test Stimulus Process
    // ---------------------------------------------------------
    initial begin
        // --- Step 1: Initialize System Triggers ---
        CLK            = 0;
        RESET          = 1;
        RegWriteE      = 0;
        ResultSrcE     = 2'b00;
        MemWriteE      = 0;
        BranchE        = 0;
        JalE           = 0;
        JalrE          = 0;
        ALUSrcE        = 0;
        ALUControlE    = 5'b00000;
        ShamtE         = 5'd0;
        RD1E           = 32'd0;
        RD2E           = 32'd0;
        PCE            = 32'd0;
        Imm_Ext_E      = 32'd0;
        PCPlus4E       = 32'd0;
        RDE            = 5'd0;
        RS1E           = 5'd0;
        RS2E           = 5'd0;
        ForwardAE      = 2'b00;
        ForwardBE      = 2'b00;
        ALUResultM_fwd = 32'd0;
        ResultW_fwd    = 32'd0;

        // Apply Synchronous Reset
        #20;
        RESET = 0;
        #10;

        $display("==================================================");
        $display("   STARTING TESTBENCH: EXECUTE STAGE              ");
        $display("==================================================");

        // -------------------------------------------------------------
        // Scenario 1: Standard R-Type Operation (ADD x5 = x10 + x11)
        // No forwarding active (ForwardAE=00, ForwardBE=00)
        // -------------------------------------------------------------
        $display("\n[Scenario 1] Standard R-Type ADD (No Forwarding)");
        RegWriteE   = 1'b1;
        ResultSrcE  = 2'b00;
        ALUSrcE     = 1'b0;       // Choose register data (SrcB_reg_fwd)
        ALUControlE = 5'b00110;   // ADD code
        RD1E        = 32'd15;     // rs1 value
        RD2E        = 32'd25;     // rs2 value
        RDE         = 5'd5;       // rd identifier
        PCPlus4E    = 32'h1004;
        ForwardAE   = 2'b00;
        ForwardBE   = 2'b00;
        #10; // Trigger pipeline clock transition to register outputs

        if (ALUResultM === 32'd40 && WriteDataM === 32'd25 && RegWriteM === 1'b1)
            $display(" -> SUCCESS: ADD evaluated to 40 and correctly passed to EX/MA register.");
        else
            $display(" -> FAILURE: R-Type execution error! ALUResultM=%d", ALUResultM);


        // -------------------------------------------------------------
        // Scenario 2: Operand Forwarding from Memory Stage (ForwardAE = 2'b10)
        // Operand A should instantly intercept data from ALUResultM_fwd
        // -------------------------------------------------------------
        $display("\n[Scenario 2] Forwarding from Memory Stage to SrcA");
        ALUResultM_fwd = 32'd100; // Expected forwarded value
        ForwardAE      = 2'b10;   // Select ALUResultM_fwd
        ForwardBE      = 2'b00;   // Keep raw register value for SrcB (25)
        #10;

        if (ALUResultM === 32'd125) // 100 + 25 = 125
            $display(" -> SUCCESS: Memory stage forwarding bypass applied perfectly to SrcA.");
        else
            $display(" -> FAILURE: Forwarding A failed! ALUResultM=%d (Expected: 125)", ALUResultM);


        // -------------------------------------------------------------
        // Scenario 3: Operand Forwarding from Writeback Stage (ForwardBE = 2'b01)
        // Operand B should intercept data from ResultW_fwd
        // -------------------------------------------------------------
        $display("\n[Scenario 3] Forwarding from Writeback Stage to SrcB");
        ForwardAE   = 2'b00;   // Reset A back to raw register (15)
        ResultW_fwd = 32'd200; // Expected forwarded value
        ForwardBE   = 2'b01;   // Select ResultW_fwd
        #10;

        if (ALUResultM === 32'd215) // 15 + 200 = 215
            $display(" -> SUCCESS: Writeback stage forwarding bypass applied perfectly to SrcB.");
        else
            $display(" -> FAILURE: Forwarding B failed! ALUResultM=%d (Expected: 215)", ALUResultM);


        // -------------------------------------------------------------
        // Scenario 4: I-Type Processing with Immediate Offset (ALUSrcE = 1)
        // SrcB must switch over to Imm_Ext_E instead of register variants
        // -------------------------------------------------------------
        $display("\n[Scenario 4] Immediate Extension Evaluation (ALUSrcE = 1)");
        ALUSrcE   = 1'b1;         // Route Immediate 
        Imm_Ext_E = 32'd50;       // Offset value
        ForwardBE = 2'b00;       // Turn off forwarding selectors
        #10;

        if (ALUResultM === 32'd65) // 15 (RD1E) + 50 (Imm) = 65
            $display(" -> SUCCESS: Immediate routed successfully into ALU computation stream.");
        else
            $display(" -> FAILURE: Immediate mux selection failed! ALUResultM=%d", ALUResultM);


        // -------------------------------------------------------------
        // Scenario 5: Conditional Branch Evaluated True (BEQ Taken)
        // Setup Equal operands -> Zero=1 -> Branch Taken -> PCSrcE = 2'b01
        // -------------------------------------------------------------
        $display("\n[Scenario 5] Branch Condition Processing (BEQ Taken)");
        ALUSrcE     = 1'b0;
        ALUControlE = 5'b00001;   // BEQ substraction code
        RD1E        = 32'd77;
        RD2E        = 32'd77;     // Force matching records for equality
        BranchE     = 1'b1;
        PCE         = 32'h2000;
        Imm_Ext_E   = 32'h0010;   // Branch Offset (+16 bytes)
        #10;

        if (PCSrcE === 2'b01 && PCTargetE === 32'h2010)
            $display(" -> SUCCESS: BEQ evaluated taken. Control flagged PC jump target to 0x2010.");
        else
            $display(" -> FAILURE: Branch miscalculation! PCSrcE=%b, PCTargetE=%h", PCSrcE, PCTargetE);

        BranchE = 1'b0; // Clear flag


        // -------------------------------------------------------------
        // Scenario 6: Unconditional Jump Register Execution (JALR)
        // JALR instantly forces PCSrcE = 2'b10 and passes target via ResultE
        // -------------------------------------------------------------
        $display("\n[Scenario 6] JALR Unconditional Jump Evaluation");
        JalrE       = 1'b1;
        ALUControlE = 5'b00010;   // JALR address generation code (Base + Offset)
        RD1E        = 32'h3000;   // Base Address
        Imm_Ext_E   = 32'h0008;   // Immediate Offset
        #10;

        if (PCSrcE === 2'b10 && ResultE === 32'h3008)
            $display(" -> SUCCESS: JALR forced direct hardware PC redirect vector to 0x3008.");
        else
            $display(" -> FAILURE: JALR verification failed! PCSrcE=%b, ResultE=%h", PCSrcE, ResultE);


        // --- End Simulation ---
        $display("\n==================================================");
        $display("   TESTBENCH COMPLETED: EXECUTE STAGE             ");
        $display("==================================================");
        $finish;
    end

    // ---------------------------------------------------------
    // 6. GTKWave Structural Trace Setup
    // ---------------------------------------------------------
    initial begin
        $dumpfile("execute_stage_tb.vcd");
        // Dump all signals including inner ALU multiplexer nodes
        $dumpvars(0, tb_execute_stage);
    end

endmodule

execute_stage_tb.vcd
$date
	Tue Jun 23 08:38:13 2026
$end
$version
	Icarus Verilog
$end
$timescale
	1ps
$end
$scope module tb_execute_stage $end
$var wire 32 ! WriteDataM [31:0] $end
$var wire 2 " ResultSrcM [1:0] $end
$var wire 32 # ResultE [31:0] $end
$var wire 1 $ RegWriteM $end
$var wire 5 % RDM [4:0] $end
$var wire 32 & PCTargetE [31:0] $end
$var wire 2 ' PCSrcE [1:0] $end
$var wire 32 ( PCPlus4M [31:0] $end
$var wire 1 ) MemWriteM $end
$var wire 32 * ALUResultM [31:0] $end
$var reg 5 + ALUControlE [4:0] $end
$var reg 32 , ALUResultM_fwd [31:0] $end
$var reg 1 - ALUSrcE $end
$var reg 1 . BranchE $end
$var reg 1 / CLK $end
$var reg 2 0 ForwardAE [1:0] $end
$var reg 2 1 ForwardBE [1:0] $end
$var reg 32 2 Imm_Ext_E [31:0] $end
$var reg 1 3 JalE $end
$var reg 1 4 JalrE $end
$var reg 1 5 MemWriteE $end
$var reg 32 6 PCE [31:0] $end
$var reg 32 7 PCPlus4E [31:0] $end
$var reg 32 8 RD1E [31:0] $end
$var reg 32 9 RD2E [31:0] $end
$var reg 5 : RDE [4:0] $end
$var reg 1 ; RESET $end
$var reg 5 < RS1E [4:0] $end
$var reg 5 = RS2E [4:0] $end
$var reg 1 > RegWriteE $end
$var reg 2 ? ResultSrcE [1:0] $end
$var reg 32 @ ResultW_fwd [31:0] $end
$var reg 5 A ShamtE [4:0] $end
$scope module uut $end
$var wire 5 B ALUControlE [4:0] $end
$var wire 32 C ALUResultM_fwd [31:0] $end
$var wire 1 - ALUSrcE $end
$var wire 1 . BranchE $end
$var wire 1 / CLK $end
$var wire 2 D ForwardAE [1:0] $end
$var wire 2 E ForwardBE [1:0] $end
$var wire 32 F Imm_Ext_E [31:0] $end
$var wire 1 3 JalE $end
$var wire 1 4 JalrE $end
$var wire 1 5 MemWriteE $end
$var wire 32 G PCE [31:0] $end
$var wire 32 H PCPlus4E [31:0] $end
$var wire 32 I RD1E [31:0] $end
$var wire 32 J RD2E [31:0] $end
$var wire 5 K RDE [4:0] $end
$var wire 1 ; RESET $end
$var wire 5 L RS1E [4:0] $end
$var wire 5 M RS2E [4:0] $end
$var wire 1 > RegWriteE $end
$var wire 32 N ResultE [31:0] $end
$var wire 2 O ResultSrcE [1:0] $end
$var wire 32 P ResultW_fwd [31:0] $end
$var wire 5 Q ShamtE [4:0] $end
$var wire 1 R Zero $end
$var wire 32 S SrcB [31:0] $end
$var wire 32 T PCTargetE [31:0] $end
$var wire 2 U PCSrcE [1:0] $end
$var wire 32 V ALUResult [31:0] $end
$var reg 32 W ALUResultM [31:0] $end
$var reg 1 ) MemWriteM $end
$var reg 32 X PCPlus4M [31:0] $end
$var reg 5 Y RDM [4:0] $end
$var reg 1 $ RegWriteM $end
$var reg 2 Z ResultSrcM [1:0] $end
$var reg 32 [ SrcA_raw [31:0] $end
$var reg 32 \ SrcB_reg_fwd [31:0] $end
$var reg 32 ] WriteDataM [31:0] $end
$scope module u_alu $end
$var wire 5 ^ ALUControl [4:0] $end
$var wire 5 _ Shamt [4:0] $end
$var wire 32 ` SrcA [31:0] $end
$var wire 32 a SrcB [31:0] $end
$var wire 1 R Zero $end
$var reg 32 b ALUResult [31:0] $end
$upscope $end
$scope module u_pcsrc $end
$var wire 5 c ALUControlE [4:0] $end
$var wire 1 . BranchE $end
$var wire 1 3 JalE $end
$var wire 1 4 JalrE $end
$var wire 1 R Zero $end
$var reg 2 d PCSrcE [1:0] $end
$var reg 1 e branch_taken $end
$upscope $end
$upscope $end
$upscope $end
$enddefinitions $end
$comment Show the parameter values. $end
$dumpall
$end
#0
$dumpvars
0e
b0 d
b0 c
b0 b
b0 a
b0 `
b0 _
b0 ^
b0 ]
b0 \
b0 [
b0 Z
b0 Y
b0 X
b0 W
b0 V
b0 U
b0 T
b0 S
1R
b0 Q
b0 P
b0 O
b0 N
b0 M
b0 L
b0 K
b0 J
b0 I
b0 H
b0 G
b0 F
b0 E
b0 D
b0 C
b0 B
b0 A
b0 @
b0 ?
0>
b0 =
b0 <
1;
b0 :
b0 9
b0 8
b0 7
b0 6
05
04
03
b0 2
b0 1
b0 0
0/
0.
0-
b0 ,
b0 +
b0 *
0)
b0 (
b0 '
b0 &
b0 %
0$
b0 #
b0 "
b0 !
$end
#5000
1/
#10000
0/
#15000
1/
#20000
0/
0;
#25000
1/
#30000
b11001 S
b11001 a
0R
b101000 #
b101000 N
b101000 V
b101000 b
b11001 \
b1111 [
b1111 `
0/
b1000000000100 7
b1000000000100 H
b101 :
b101 K
b11001 9
b11001 J
b1111 8
b1111 I
b110 +
b110 B
b110 ^
b110 c
1>
#35000
b1000000000100 (
b1000000000100 X
b101 %
b101 Y
1$
b11001 !
b11001 ]
b101000 *
b101000 W
1/
#40000
b1111101 #
b1111101 N
b1111101 V
b1111101 b
b1100100 [
b1100100 `
0/
b10 0
b10 D
b1100100 ,
b1100100 C
#45000
b1111101 *
b1111101 W
1/
#50000
b11001000 S
b11001000 a
b11010111 #
b11010111 N
b11010111 V
b11010111 b
b11001000 \
b1111 [
b1111 `
0/
b1 1
b1 E
b11001000 @
b11001000 P
b0 0
b0 D
#55000
b11001000 !
b11001000 ]
b11010111 *
b11010111 W
1/
#60000
b1000001 #
b1000001 N
b1000001 V
b1000001 b
b11001 \
b110010 S
b110010 a
0/
b0 1
b0 E
b110010 &
b110010 T
b110010 2
b110010 F
1-
#65000
b11001 !
b11001 ]
b1000001 *
b1000001 W
1/
#70000
b1 '
b1 U
b1 d
1e
1R
b1001101 \
b1001101 [
b1001101 `
b0 #
b0 N
b0 V
b0 b
b1001101 S
b1001101 a
0/
b10000 2
b10000 F
b10000000010000 &
b10000000010000 T
b10000000000000 6
b10000000000000 G
1.
b1001101 9
b1001101 J
b1001101 8
b1001101 I
b1 +
b1 B
b1 ^
b1 c
0-
#75000
b1001101 !
b1001101 ]
b0 *
b0 W
1/
#80000
b11000000000000 [
b11000000000000 `
0R
b11000001001101 #
b11000001001101 N
b11000001001101 V
b11000001001101 b
0e
b10 '
b10 U
b10 d
0/
b10000000001000 &
b10000000001000 T
b1000 2
b1000 F
b11000000000000 8
b11000000000000 I
b10 +
b10 B
b10 ^
b10 c
14
0.
#85000
b11000001001101 *
b11000001001101 W
1/
