rtl/fetch_stage.v
// FETCH STAGE - IF
module fetch_stage (
    input  wire        CLK,
    input  wire        RESET,

    // From EX stage
    input  wire [1:0]  PCSrcE,
    input  wire [31:0] PCTargetE,   // PC + imm (branch/JAL)
    input  wire [31:0] ResultE,     // ALU result (JALR)

    // Hazard signals
    input  wire        enableF,     // 0=stall
    input  wire        enableD,     // 0=stall
    input  wire        clearD,      // 1=flush IF/ID register
    // Outputs to ID stage 
    output reg  [31:0] InStrD,
    output reg  [31:0] PCD,
    output reg  [31:0] PCPlus4D
);

    // PC register
    reg  [31:0] PC_reg;
    wire [31:0] PC_next;
    wire [31:0] PC_current;
    wire [31:0] PCPlus4F;
    wire [31:0] InStrF;

    assign PC_current = PC_reg;
    assign PCPlus4F   = PC_current + 32'd4;

    // 3-to-1 MUX 
    assign PC_next = (PCSrcE == 2'b10) ? ResultE   :
                     (PCSrcE == 2'b01) ? PCTargetE :
                                         PCPlus4F;

    // PC register update
    always @(posedge CLK or posedge RESET) begin
        if (RESET)
            PC_reg <= 32'h0000_0000;
        else if (enableF)
            PC_reg <= PC_next;
    end

    // Instruction Memory (ROM)

    reg [31:0] imem [0:255];

   initial begin
        $readmemh("imem32.mem", imem, 8'd0, 8'd31);
    end 

    assign InStrF = imem[PC_current[9:2]]; // word-addressed

    //   IF/ID Pipeline Register 
    always @(posedge CLK or posedge RESET) begin
        if (RESET || clearD) begin
            InStrD   <= 32'h0000_0013; // NOP 
            PCD      <= 32'd0;
            PCPlus4D <= 32'd0;
        end else if (enableD) begin
            InStrD   <= InStrF;
            PCD      <= PC_current;
            PCPlus4D <= PCPlus4F;
        end
    end

endmodule

tb/tb_fetch_stage.v
`timescale 1ns / 1ps

module tb_fetch_stage;

    // --- Inputs to the module ---
    reg        CLK;
    reg        RESET;
    reg  [1:0] PCSrcE;      // 00: PC+4, 01: Branch/JAL, 10: JALR
    reg [31:0] PCTargetE;   // Target address for branch/jump
    reg [31:0] ResultE;     // ALU result for JALR
    reg        enableF;     // PC enable signal
    reg        enableD;     // IF/ID register enable
    reg        clearD;      // IF/ID register flush (clear)

    // --- Outputs from the module ---
    wire [31:0] InStrD;
    wire [31:0] PCD;
    wire [31:0] PCPlus4D;

    // Instantiate the Unit Under Test (UUT)
    fetch_stage uut (
        .CLK(CLK), 
        .RESET(RESET),
        .PCSrcE(PCSrcE), 
        .PCTargetE(PCTargetE), 
        .ResultE(ResultE),
        .enableF(enableF), 
        .enableD(enableD), 
        .clearD(clearD),
        .InStrD(InStrD), 
        .PCD(PCD), 
        .PCPlus4D(PCPlus4D)
    );

    // Clock generation: 10ns period
    always #5 CLK = ~CLK;

    initial begin
        // --- Initialization ---
        CLK = 0;
        RESET = 1;
        PCSrcE = 2'b00;
        PCTargetE = 0;
        ResultE = 0;
        enableF = 1;
        enableD = 1;
        clearD = 0;

        // Apply reset for 20ns
        #20 RESET = 0;

        // --- 1. Normal Execution Phase ---
        $display("--- Starting Normal Execution ---");
        // Allow the PC to increment freely for 10 cycles
        repeat(10) @(posedge CLK);

        // --- 2. Stall Phase ---
        $display("--- Testing Stall (enableF=0, enableD=0) ---");
        enableF = 0; // PC stops incrementing
        enableD = 0; // Pipeline register freezes
        repeat(3) @(posedge CLK);
        
        // Resume operation
        enableF = 1;
        enableD = 1;
        repeat(2) @(posedge CLK);

        // --- 3. Branch/Jump Phase ---
        $display("--- Testing Branch (PCSrcE=01) ---");
        PCSrcE = 2'b01;
        PCTargetE = 32'h0000_0040; // Target branch address
        @(posedge CLK);
        
        // Return to normal execution after branch
        PCSrcE = 2'b00;
        repeat(3) @(posedge CLK);

        // --- 4. Flush Phase ---
        $display("--- Testing Flush (clearD=1) ---");
        clearD = 1; // Clear instruction in ID stage
        @(posedge CLK);
        clearD = 0; // Disable clear
        repeat(3) @(posedge CLK);

        // --- Finish simulation ---
        $display("--- Simulation Completed Successfully ---");
        #20 $finish;
    end

    // Monitor for terminal output
    initial begin
        $dumpfile("fetch_stage_tb.vcd");
        $dumpvars(0, tb_fetch_stage);
        
        // Print status on every clock edge
        $monitor("Time=%0t | PC=%h | Instr=%h | PCSrcE=%b | clearD=%b", 
                  $time, PCD, InStrD, PCSrcE, clearD);
    end

endmodule

fetch_stage_tb.vcd
$date
	Tue Jun 23 09:16:21 2026
$end
$version
	Icarus Verilog
$end
$timescale
	1ps
$end
$scope module tb_fetch_stage $end
$var wire 32 ! PCPlus4D [31:0] $end
$var wire 32 " PCD [31:0] $end
$var wire 32 # InStrD [31:0] $end
$var reg 1 $ CLK $end
$var reg 2 % PCSrcE [1:0] $end
$var reg 32 & PCTargetE [31:0] $end
$var reg 1 ' RESET $end
$var reg 32 ( ResultE [31:0] $end
$var reg 1 ) clearD $end
$var reg 1 * enableD $end
$var reg 1 + enableF $end
$scope module uut $end
$var wire 1 $ CLK $end
$var wire 32 , InStrF [31:0] $end
$var wire 2 - PCSrcE [1:0] $end
$var wire 32 . PCTargetE [31:0] $end
$var wire 1 ' RESET $end
$var wire 32 / ResultE [31:0] $end
$var wire 1 ) clearD $end
$var wire 1 * enableD $end
$var wire 1 + enableF $end
$var wire 32 0 PC_next [31:0] $end
$var wire 32 1 PC_current [31:0] $end
$var wire 32 2 PCPlus4F [31:0] $end
$var reg 32 3 InStrD [31:0] $end
$var reg 32 4 PCD [31:0] $end
$var reg 32 5 PCPlus4D [31:0] $end
$var reg 32 6 PC_reg [31:0] $end
$upscope $end
$upscope $end
$enddefinitions $end
$comment Show the parameter values. $end
$dumpall
$end
#0
$dumpvars
b0 6
b0 5
b0 4
b10011 3
b100 2
b0 1
b100 0
b0 /
b0 .
b0 -
b10100000000000010010011 ,
1+
1*
0)
b0 (
1'
b0 &
b0 %
0$
b10011 #
b0 "
b0 !
$end
#5000
1$
#10000
0$
#15000
1$
#20000
0$
0'
#25000
b1000 0
b1100000000000100010011 ,
b100 !
b100 5
b10100000000000010010011 #
b10100000000000010010011 3
b1000 2
b100 1
b100 6
1$
#30000
0$
#35000
b1100 0
b1000001000000110110011 ,
b1100 2
b1000 1
b1000 6
b1000 !
b1000 5
b100 "
b100 4
b1100000000000100010011 #
b1100000000000100010011 3
1$
#40000
0$
#45000
b10000 0
b1000000001000011000001000110011 ,
b1100 !
b1100 5
b1000 "
b1000 4
b1000001000000110110011 #
b1000001000000110110011 3
b10000 2
b1100 1
b1100 6
1$
#50000
0$
#55000
b10100 0
b1000001111001010110011 ,
b10100 2
b10000 1
b10000 6
b10000 !
b10000 5
b1100 "
b1100 4
b1000000001000011000001000110011 #
b1000000001000011000001000110011 3
1$
#60000
0$
#65000
b11000 0
b1000001110001100110011 ,
b10100 !
b10100 5
b10000 "
b10000 4
b1000001111001010110011 #
b1000001111001010110011 3
b11000 2
b10100 1
b10100 6
1$
#70000
0$
#75000
b11100 0
b1000001100001110110011 ,
b11100 2
b11000 1
b11000 6
b11000 !
b11000 5
b10100 "
b10100 4
b1000001110001100110011 #
b1000001110001100110011 3
1$
#80000
0$
#85000
b100000 0
b1000001001010000110011 ,
b11100 !
b11100 5
b11000 "
b11000 4
b1000001100001110110011 #
b1000001100001110110011 3
b100000 2
b11100 1
b11100 6
1$
#90000
0$
#95000
b100100 0
b110010000000000010010010011 ,
b100100 2
b100000 1
b100000 6
b100000 !
b100000 5
b11100 "
b11100 4
b1000001001010000110011 #
b1000001001010000110011 3
1$
#100000
0$
#105000
b101000 0
b101001000000000100011 ,
b100100 !
b100100 5
b100000 "
b100000 4
b110010000000000010010010011 #
b110010000000000010010010011 3
b101000 2
b100100 1
b100100 6
1$
#110000
0$
#115000
0*
0+
1$
#120000
0$
#125000
1$
#130000
0$
#135000
1$
#140000
0$
#145000
b101100 0
b1001000010100000011 ,
b101000 !
b101000 5
b100100 "
b100100 4
b101001000000000100011 #
b101001000000000100011 3
b101100 2
b101000 1
b101000 6
1*
1+
1$
#150000
0$
#155000
b110000 0
b101010000010100010011 ,
b110000 2
b101100 1
b101100 6
b101100 !
b101100 5
b101000 "
b101000 4
b1001000010100000011 #
b1001000010100000011 3
1$
#160000
0$
#165000
b10110010011 ,
b110000 !
b110000 5
b101100 "
b101100 4
b101010000010100010011 #
b101010000010100010011 3
b110100 2
b110000 1
b110000 6
b1000000 0
b1000000 &
b1000000 .
b1 %
b1 -
1$
#170000
0$
#175000
b1110001010001100011 ,
b1000100 2
b1000000 1
b1000000 6
b110100 !
b110100 5
b110000 "
b110000 4
b10110010011 #
b10110010011 3
b1000100 0
b0 %
b0 -
1$
#180000
0$
#185000
b1001000 0
b110001100000000011110010011 ,
b1000100 !
b1000100 5
b1000000 "
b1000000 4
b1110001010001100011 #
b1110001010001100011 3
b1001000 2
b1000100 1
b1000100 6
1$
#190000
0$
#195000
b1001100 0
b11011100000000100000010011 ,
b1001100 2
b1001000 1
b1001000 6
b1001000 !
b1001000 5
b1000100 "
b1000100 4
b110001100000000011110010011 #
b110001100000000011110010011 3
1$
#200000
0$
#205000
b1010000 0
b100000000000100011101111 ,
b0 !
b0 5
b0 "
b0 4
b10011 #
b10011 3
b1010000 2
b1001100 1
b1001100 6
1)
1$
#210000
0$
#215000
b1010100 0
b110001100000000100100010011 ,
b1010100 2
b1010000 1
b1010000 6
b1010000 !
b1010000 5
b1001100 "
b1001100 4
b100000000000100011101111 #
b100000000000100011101111 3
0)
1$
#220000
0$
#225000
b1011000 0
b100110100000000100110010011 ,
b1010100 !
b1010100 5
b1010000 "
b1010000 4
b110001100000000100100010011 #
b110001100000000100100010011 3
b1011000 2
b1010100 1
b1010100 6
1$
#230000
0$
#235000
b1011100 0
b10010001101000101001010110111 ,
b1011100 2
b1011000 1
b1011000 6
b1011000 !
b1011000 5
b1010100 "
b1010100 4
b100110100000000100110010011 #
b100110100000000100110010011 3
1$
#240000
0$
#245000
b1100000 0
b100000001100010111 ,
b1011100 !
b1011100 5
b1011000 "
b1011000 4
b10010001101000101001010110111 #
b10010001101000101001010110111 3
b1100000 2
b1011100 1
b1011100 6
1$
#250000
0$
#255000
b1100100 0
b11110000000000101000001110010011 ,
b1100100 2
b1100000 1
b1100000 6
b1100000 !
b1100000 5
b1011100 "
b1011100 4
b100000001100010111 #
b100000001100010111 3
1$
#260000
0$
#265000
b1101000 0
b10000111001010000010011 ,
b1100100 !
b1100100 5
b1100000 "
b1100000 4
b11110000000000101000001110010011 #
b11110000000000101000001110010011 3
b1101000 2
b1100100 1
b1100100 6
1$
